deepclustering/__init__.py
deepclustering/manager.py
deepclustering/arch/__init__.py
deepclustering/arch/classification/__init__.py
deepclustering/arch/classification/dummy.py
deepclustering/arch/classification/preresnet.py
deepclustering/arch/classification/vat_network.py
deepclustering/arch/classification/vgg16_bn.py
deepclustering/arch/classification/IIC/__init__.py
deepclustering/arch/classification/IIC/net5g.py
deepclustering/arch/classification/IIC/net5g_multi_head.py
deepclustering/arch/classification/IIC/net5g_two_head.py
deepclustering/arch/classification/IIC/net6c.py
deepclustering/arch/classification/IIC/net6c_two_head.py
deepclustering/arch/classification/IIC/residual.py
deepclustering/arch/classification/IIC/vgg.py
deepclustering/arch/classification/IIC/baselines/__init__.py
deepclustering/arch/classification/IIC/baselines/triplets.py
deepclustering/arch/classification/IMSAT/__init__.py
deepclustering/arch/classification/IMSAT/imsat.py
deepclustering/arch/segmentation/__init__.py
deepclustering/arch/segmentation/attention_unet.py
deepclustering/arch/segmentation/enet.py
deepclustering/arch/segmentation/network.py
deepclustering/arch/segmentation/vnet.py
deepclustering/arch/segmentation/deeplab/__init__.py
deepclustering/arch/segmentation/deeplab/deeplabv2.py
deepclustering/arch/segmentation/deeplab/deeplabv3.py
deepclustering/arch/segmentation/deeplab/deeplabv3plus.py
deepclustering/arch/segmentation/deeplab/enet.py
deepclustering/arch/segmentation/deeplab/msc.py
deepclustering/arch/segmentation/deeplab/resnet.py
deepclustering/arch/segmentation/epsnetv2/Model.py
deepclustering/arch/segmentation/epsnetv2/SegmentationModel.py
deepclustering/arch/segmentation/epsnetv2/__init__.py
deepclustering/arch/segmentation/epsnetv2/cnn_utils.py
deepclustering/arch/segmentation/joseent/__init__.py
deepclustering/arch/segmentation/joseent/layers.py
deepclustering/arch/segmentation/joseent/networks.py
deepclustering/augment/__init__.py
deepclustering-0.0.3.dist-info/LICENSE
deepclustering-0.0.3.dist-info/METADATA
deepclustering-0.0.3.dist-info/WHEEL
deepclustering-0.0.3.dist-info/entry_points.txt
deepclustering-0.0.3.dist-info/top_level.txt
deepclustering-0.0.3.dist-info/RECORD
