Metadata-Version: 2.1
Name: deepclustering
Version: 0.0.3
Summary: UNKNOWN
Home-page: https://github.com/jizongFox/deep-clustering-toolbox
Author: Jizong Peng
Author-email: jizong.peng.1@etsmtl.net
License: MIT
Platform: UNKNOWN
Requires-Dist: msgpack
Requires-Dist: numpy
Requires-Dist: torch
Requires-Dist: torchvision
Requires-Dist: Pillow
Requires-Dist: scikit-learn
Requires-Dist: behave
Requires-Dist: requests
Requires-Dist: scikit-image
Requires-Dist: pandas
Requires-Dist: easydict
Requires-Dist: matplotlib
Requires-Dist: tqdm (==4.32.2)
Requires-Dist: py (==1.8.0)
Requires-Dist: pytest-remotedata (==0.3.1)
Requires-Dist: tensorboardX
Requires-Dist: tensorboard
Requires-Dist: opencv-python
Requires-Dist: medpy
Requires-Dist: pyyaml
Requires-Dist: termcolor
Requires-Dist: gpuqueue
Requires-Dist: gdown
